sitecustomize/__init__.py
sitecustomize/_utils.py
sitecustomize/_vendor/__init__.py
sitecustomize/_vendor/importlib_metadata/LICENSE
sitecustomize/_vendor/importlib_metadata/__init__.py
sitecustomize/_vendor/importlib_metadata/_adapters.py
sitecustomize/_vendor/importlib_metadata/_collections.py
sitecustomize/_vendor/importlib_metadata/_compat.py
sitecustomize/_vendor/importlib_metadata/_functools.py
sitecustomize/_vendor/importlib_metadata/_itertools.py
sitecustomize/_vendor/importlib_metadata/_meta.py
sitecustomize/_vendor/importlib_metadata/_text.py
sitecustomize/_vendor/importlib_metadata/py.typed
sitecustomize/_vendor/vendor.txt
sitecustomize/_vendor/zipp.LICENSE
sitecustomize/_vendor/zipp.py
sitecustomize/_vendor/zipp.pyi
sitecustomize_entrypoints-1.1.0.dist-info/WHEEL
sitecustomize_entrypoints-1.1.0.dist-info/METADATA
sitecustomize_entrypoints-1.1.0.dist-info/RECORD
