Metadata-Version: 2.1
Name: sitecustomize-entrypoints
Version: 1.1.0
Summary: Sitecustomize-module that executes all correctly registered ``sitecustomize``-entypoints.
Home-page: https://github.com/Darsstar/sitecustomize-entrypoints
License: MIT
Keywords: entrypoints,sitecustomize
Author: Dos Moonen
Author-email: d.moonen@nki.nl
Maintainer: Dos Moonen
Maintainer-email: d.moonen@nki.nl
Requires-Python: >=3.7.2
Classifier: Development Status :: 4 - Beta
Classifier: Environment :: Console
Classifier: Intended Audience :: Developers
Classifier: License :: OSI Approved :: MIT License
Classifier: Operating System :: POSIX :: Linux
Classifier: Programming Language :: Python :: 3
Classifier: Programming Language :: Python :: 3.8
Classifier: Programming Language :: Python :: 3.9
Classifier: Programming Language :: Python :: 3.10
Classifier: Programming Language :: Python :: 3.10
Classifier: Programming Language :: Python :: 3.11
Classifier: Programming Language :: Python :: 3.8
Classifier: Programming Language :: Python :: 3.9
Classifier: Programming Language :: Python :: Implementation :: CPython
Classifier: Programming Language :: Python :: Implementation :: PyPy
Classifier: Typing :: Typed
Project-URL: Documentation, https://sitecustomize-entrypoints.readthedocs.io
Project-URL: Repository, https://github.com/Darsstar/sitecustomize-entrypoints
